pygifmaker/__init__.py
pygifmaker/pygifmaker.py
pypygifmaker-0.0.1.2.dist-info/LICENSE.txt
pypygifmaker-0.0.1.2.dist-info/METADATA
pypygifmaker-0.0.1.2.dist-info/WHEEL
pypygifmaker-0.0.1.2.dist-info/top_level.txt
pypygifmaker-0.0.1.2.dist-info/RECORD
