Metadata-Version: 2.1
Name: pypygifmaker
Version: 0.0.1.2
Summary: You can make a simple gif easily with this GIFMAKER
Home-page: https://github.com/yoonhero/gifmaker
Author: Yoonhero
Author-email: yoonhero06@naver.com
License: MIT
Project-URL: Bug Tracker, https://github.com/schooldevops/gifmaker
Platform: UNKNOWN
Classifier: Programming Language :: Python :: 3
Classifier: License :: OSI Approved :: MIT License
Classifier: Operating System :: OS Independent
Requires-Python: >=3.6
License-File: LICENSE.txt
Requires-Dist: Pillow
